{
"ModifiedBy": "",
"ModifiedDate": "8/10/2018",
"Metadata": [
{
"Id": "21",
"Filename": "9.jpg",
"Comments": "",
"Images": "http://globalreadinessfileshare.blob.core.windows.net/imagereview/2018-08-09_EDU1_JonChoe/9.jpg?sv=2014-02-14&sr=b&sig=lZX6OYWC8CugdH21x%2FDUDeQ7oHUzSXx6d0DbfHI2PAs%3D&st=2018-08-10T00%3A14%3A51Z&se=2023-08-10T00%3A19%3A51Z&sp=rw",
"DesignerComments": "21",
"CelaComments": "",
"GeopolFullMarketComments": "",
"LSPComments": "",
"ThemeCategories": "",
"TargetMarkets": ""
},
{
"Id": "22",
"Filename": "Apr.jpg",
"Comments": "",
"Images": "http://globalreadinessfileshare.blob.core.windows.net/imagereview/2018-08-09_EDU1_JonChoe/Apr.jpg?sv=2014-02-14&sr=b&sig=YzSozF5GcnKHq3ystxr8WNdfABGh132HUCKtUu38gO4%3D&st=2018-08-10T00%3A14%3A51Z&se=2023-08-10T00%3A19%3A51Z&sp=rw",
"DesignerComments": "",
"CelaComments": "",
"GeopolFullMarketComments": "",
"LSPComments": "",
"ThemeCategories": "",
"TargetMarkets": ""
},
{
"Id": "23",
"Filename": "Picture30.png",
"Comments": "",
"Images": "http://globalreadinessfileshare.blob.core.windows.net/imagereview/2018-08-09_EDU1_JonChoe/Picture30.png?sv=2014-02-14&sr=b&sig=mpSrWdXzlmpv9v%2BOkE3cbzQFJsbjtEVqq3kpIKRLNic%3D&st=2018-08-10T00%3A14%3A51Z&se=2023-08-10T00%3A19%3A51Z&sp=rw",
"DesignerComments": "",
"CelaComments": "",
"GeopolFullMarketComments": "",
"LSPComments": "",
"ThemeCategories": "",
"TargetMarkets": ""
},
{
"Id": "24",
"Filename": "18.jpg",
"Comments": "",
"Images": "http://globalreadinessfileshare.blob.core.windows.net/imagereview/2018-08-09_EDU1_JonChoe/18.jpg?sv=2014-02-14&sr=b&sig=Eum3DG2qZcNhIPqlvERs9IyYkAzmONOVFv1FmY6Qroc%3D&st=2018-08-10T00%3A14%3A51Z&se=2023-08-10T00%3A19%3A51Z&sp=rw",
"DesignerComments": "",
"CelaComments": "",
"GeopolFullMarketComments": "",
"LSPComments": "",
"ThemeCategories": "",
"TargetMarkets": ""
},
{
"Id": "25",
"Filename": "2.jpg",
"Comments": "",
"Images": "http://globalreadinessfileshare.blob.core.windows.net/imagereview/2018-08-09_EDU1_JonChoe/2.jpg?sv=2014-02-14&sr=b&sig=vjv7u%2FF6CiYO%2Fcrxx5w2Bb9%2BtycCIbPxnxrVEL1H8Ps%3D&st=2018-08-10T00%3A14%3A51Z&se=2023-08-10T00%3A19%3A51Z&sp=rw",
"DesignerComments": "",
"CelaComments": "",
"GeopolFullMarketComments": "",
"LSPComments": "",
"ThemeCategories": "",
"TargetMarkets": ""
},
{
"Id": "26",
"Filename": "6.jpg",
"Comments": "",
"Images": "http://globalreadinessfileshare.blob.core.windows.net/imagereview/2018-08-09_EDU1_JonChoe/6.jpg?sv=2014-02-14&sr=b&sig=KRmvJfaAUUgGFgJGTi5TGV%2BKFmsI9W%2BQKNMEu%2BytdLo%3D&st=2018-08-10T00%3A14%3A51Z&se=2023-08-10T00%3A19%3A51Z&sp=rw",
"DesignerComments": "",
"CelaComments": "",
"GeopolFullMarketComments": "",
"LSPComments": "",
"ThemeCategories": "",
"TargetMarkets": ""
},
{
"Id": "27",
"Filename": "delete.JPG",
"Comments": "",
"Images": "http://globalreadinessfileshare.blob.core.windows.net/imagereview/2018-08-09_EDU1_JonChoe/delete.JPG?sv=2014-02-14&sr=b&sig=ryxcRBurSqmo1ksEx0dpYhIjn%2B28HDdWBuVk%2BCeeGmk%3D&st=2018-08-10T00%3A14%3A51Z&se=2023-08-10T00%3A19%3A51Z&sp=rw",
"DesignerComments": "",
"CelaComments": "",
"GeopolFullMarketComments": "",
"LSPComments": "",
"ThemeCategories": "",
"TargetMarkets": ""
},
{
"Id": "28",
"Filename": "May1.jpg",
"Comments": "",
"Images": "http://globalreadinessfileshare.blob.core.windows.net/imagereview/2018-08-09_EDU1_JonChoe/May1.jpg?sv=2014-02-14&sr=b&sig=KyWNMixenOwdHPjeUZ9dJRM5l430IeyolxShNN1s9o0%3D&st=2018-08-10T00%3A14%3A52Z&se=2023-08-10T00%3A19%3A52Z&sp=rw",
"DesignerComments": "",
"CelaComments": "",
"GeopolFullMarketComments": "",
"LSPComments": "",
"ThemeCategories": "",
"TargetMarkets": ""
},
{
"Id": "29",
"Filename": "th92HP8PGH.jpg",
"Comments": "",
"Images": "http://globalreadinessfileshare.blob.core.windows.net/imagereview/2018-08-09_EDU1_JonChoe/th92HP8PGH.jpg?sv=2014-02-14&sr=b&sig=pwmxk72fYPQ%2B4f41GeiTlNGpJ5AgAW7fGwyJUBn1x80%3D&st=2018-08-10T00%3A14%3A52Z&se=2023-08-10T00%3A19%3A52Z&sp=rw",
"DesignerComments": "",
"CelaComments": "",
"GeopolFullMarketComments": "",
"LSPComments": "",
"ThemeCategories": "",
"TargetMarkets": ""
},
{
"Id": "30",
"Filename": "globalrequirements1.jpg",
"Comments": "",
"Images": "http://globalreadinessfileshare.blob.core.windows.net/imagereview/2018-08-09_EDU1_JonChoe/globalrequirements1.jpg?sv=2014-02-14&sr=b&sig=OWzw7X8W2hdbhiY6WhZrjdBQZeolYXVLTyS5e5BWVvA%3D&st=2018-08-10T00%3A14%3A52Z&se=2023-08-10T00%3A19%3A52Z&sp=rw",
"DesignerComments": "",
"CelaComments": "",
"GeopolFullMarketComments": "",
"LSPComments": "",
"ThemeCategories": "",
"TargetMarkets": ""
},
]
}
